src/__init__.py
src/ctrl_citylist.py
src/ctrl_poidetail.py
src/ctrl_poilist.py
src/ctrl_portal.py
src/main_citylist.py
src/main_poidetail.py
src/main_poilist.py
src/main_portal.py
src/common/__init__.py
src/common/cache.py
src/common/chameleon.py
src/common/httper.py
src/common/models.py
src/common/pyecho.py
src/common/utils.py
mafengwo_crawlers-1.2.3.dist-info/LICENSE
mafengwo_crawlers-1.2.3.dist-info/METADATA
mafengwo_crawlers-1.2.3.dist-info/WHEEL
mafengwo_crawlers-1.2.3.dist-info/top_level.txt
mafengwo_crawlers-1.2.3.dist-info/RECORD
