Metadata-Version: 2.1
Name: mafengwo-crawlers
Version: 1.2.3
Summary: 设计这个爬虫系统的主要目的是，完整快速地获取国内所有旅游目的地和旅游景点，包括名称、介绍、图片、相关攻略等。主要使用到的技术（工具／语言／库）包括：Docker, Redis, MySQL, Python, requests, peewee等。
Home-page: https://github.com/yanjlee/mafengwo-crawlers
Author: yanjlee
Author-email: yanjlee@163.com
Classifier: Programming Language :: Python :: 3
Classifier: License :: OSI Approved :: MIT License
Classifier: Operating System :: OS Independent
License-File: LICENSE
Requires-Dist: requests
Requires-Dist: faker
Requires-Dist: execjs
Requires-Dist: loguru
Requires-Dist: base64
Requires-Dist: hashlib
Requires-Dist: Crypto
Requires-Dist: pandas
Requires-Dist: fuzzywuzzy
Requires-Dist: httpx
Requires-Dist: Pillow
Requires-Dist: playwright
Requires-Dist: PyExecJS
Requires-Dist: redis
Requires-Dist: fastapi
Requires-Dist: uvicorn
Requires-Dist: APScheduler
Requires-Dist: beautifulsoup4
Requires-Dist: bs4
Requires-Dist: certifi
Requires-Dist: clickhouse-driver
Requires-Dist: curl-cffi
Requires-Dist: DrissionPage
Requires-Dist: fake-useragent
Requires-Dist: Flask
Requires-Dist: Flask-APScheduler
Requires-Dist: Flask-Cors
Requires-Dist: frida
Requires-Dist: gevent
Requires-Dist: Jinja2
Requires-Dist: langchain
Requires-Dist: langchain-community
Requires-Dist: suiutils-py
